wavclassify/__init__.py
wavclassify/__main__.py
wavclassify/browser_tools.py
wavclassify/cli.py
wavclassify/click.wav
wavclassify/click_sound.py
wavclassify/gui.py
wavclassify/lib.py
wavclassify/.vscode/settings.json
wavclassify-0.4.2.dist-info/entry_points.txt
wavclassify-0.4.2.dist-info/LICENSE
wavclassify-0.4.2.dist-info/WHEEL
wavclassify-0.4.2.dist-info/METADATA
wavclassify-0.4.2.dist-info/RECORD
